dash_dict_callback/__init__.py
dash_dict_callback/__version__.py
dash_dict_callback-0.0.2.dist-info/LICENSE
dash_dict_callback-0.0.2.dist-info/METADATA
dash_dict_callback-0.0.2.dist-info/WHEEL
dash_dict_callback-0.0.2.dist-info/top_level.txt
dash_dict_callback-0.0.2.dist-info/RECORD
